pydash/__init__.py
pydash_abhi-1.0.0.dist-info/LICENSE
pydash_abhi-1.0.0.dist-info/METADATA
pydash_abhi-1.0.0.dist-info/WHEEL
pydash_abhi-1.0.0.dist-info/top_level.txt
pydash_abhi-1.0.0.dist-info/RECORD
