Metadata-Version: 2.1
Name: pydash-abhi
Version: 1.0.0
Summary: A small clone of lodash
Home-page: https://github.com/abhijeettalele/pydash
Author-email: abhijeet.talele@gmail.com
License: UNKNOWN
Keywords: lodash,string,manipulation
Platform: UNKNOWN
Classifier: License :: OSI Approved :: MIT License
Classifier: Intended Audience :: Developers
Classifier: Programming Language :: Python :: 3 :: Only
License-File: LICENSE
